MANIFEST.in
README.md
setup.cfg
setup.py
bitrue/__init__.py
bitrue/__version__.py
bitrue/client.py
bitrue/enums.py
bitrue/exceptions.py
bitrue/helpers.py
bitrue/examples/__init__.py
bitrue/examples/check_open_orders.py
bitrue/examples/full_trade_cycle.py
bitrue/examples/historical_trades.py
bitrue/examples/trades_to_csv.py
bitrue_python.egg-info/PKG-INFO
bitrue_python.egg-info/SOURCES.txt
bitrue_python.egg-info/dependency_links.txt
bitrue_python.egg-info/not-zip-safe
bitrue_python.egg-info/requires.txt
bitrue_python.egg-info/top_level.txt